[
  {
    "type": "sound",
    "repetition": 0,
    "probability": 100,
    "sequence": [
      {
        "soundId": "start",
        "transition": null,
        "transitionDuration": null,
        "playDuration": null,
        "soundLevel": 50
      }
    ]
  },
  {
    "type": "light",
    "repetition": 0,
    "probability": 100,
    "sequence": [
      {
        "leftEye": 999,
        "rightEye": 999,
        "smile": "0,0,0",
        "transition": "fade",
        "transitionDuration": 500,
        "finalDuration": 0
      }
    ]
  },
  {
    "type": "light",
    "repetition": 29,
    "probability": 100,
    "sequence": [
      {
        "leftEye": 999,
        "rightEye": 999,
        "smile": "0,0,0",
        "transition": "fade",
        "transitionDuration": 100,
        "finalDuration": 0
      }
    ]
  },
  {
    "type": "light",
    "repetition": 0,
    "probability": 100,
    "sequence": [
      {
        "leftEye": 888,
        "rightEye": 888,
        "smile": "0,0,0",
        "transition": "fade",
        "transitionDuration": 500,
        "finalDuration": 1000
      }
    ]
  }
]
